MANIFEST.in
README.md
setup.py
dash_renderer/__init__.py
dash_renderer/bundle.js
dash_renderer/react-dom@15.4.2.min.js
dash_renderer/react-dom@16.2.0.production.min.js
dash_renderer/react@15.4.2.min.js
dash_renderer/react@16.2.0.production.min.js
dash_renderer/version.py
dash_renderer_grasia.egg-info/PKG-INFO
dash_renderer_grasia.egg-info/SOURCES.txt
dash_renderer_grasia.egg-info/dependency_links.txt
dash_renderer_grasia.egg-info/top_level.txt