Metadata-Version: 1.0
Name: dash-renderer-grasia
Version: 0.13.2
Summary: Front-end component renderer for dash
Home-page: UNKNOWN
Author: Akronix
Author-email: UNKNOWN
License: MIT
Platform: UNKNOWN
